picounits/__init__.py
picounits-0.0.1.dist-info/METADATA
picounits-0.0.1.dist-info/WHEEL
picounits-0.0.1.dist-info/licenses/LICENSE
picounits-0.0.1.dist-info/RECORD
