Metadata-Version: 2.4
Name: PicoUnits
Version: 0.0.1
Summary: SI Based Unit System With Minimal Overhead And Maximal Speed
Project-URL: Homepage, https://github.com/wgbowley/picounits
Project-URL: Bug Tracker, https://github.com/wgbowley/picounits/issues
Author-email: William Bowley <wgrantbowley@gmail.com>
Maintainer-email: William Bowley <wgrantbowley@gmail.com>
License: MIT License
License-File: LICENSE
Keywords: high-performance,minimal,physics,si,units
